{"fname":"client_key.pem.enc","flink":"C:\\Temp\\ssl\\new\\client_key.pem.enc","fbyte":"1744","ftype":".enc","ftime":"2016-11-30 오후 2:49:22","link":[{"fname":"AgentBase.exe","flink":"C:\\Temp\\AgentBase.exe","fbyte":"10707320","ftype":".exe","ftime":"2018-03-23 오후 3:35:32"},{"fname":"AgentSet.ini","flink":"C:\\Temp\\AgentSet.ini","fbyte":"554","ftype":".ini","ftime":"2018-03-23 오후 3:35:32"},{"fname":"AgentSet.sec","flink":"C:\\Temp\\AgentSet.sec","fbyte":"352","ftype":".sec","ftime":"2018-03-23 오후 3:35:32"},{"fname":"file_list.json","flink":"C:\\Temp\\file_list.json","fbyte":"4744","ftype":".json","ftime":"2018-11-27 오후 5:56:00"},{"fname":"PV3.txt","flink":"C:\\Temp\\PV3.txt","fbyte":"2288","ftype":".txt","ftime":"2018-03-29 오전 9:52:24"},{"fname":"Selectou.dat","flink":"C:\\Temp\\Selectou.dat","fbyte":"11844","ftype":".dat","ftime":"2017-10-20 오후 2:47:54"},{"fname":"panja.pj","flink":"C:\\Temp\\example\\dir\\panja.pj","fbyte":"0","ftype":".pj","ftime":"2018-10-30 오후 5:37:36"},{"fname":"hupdate.cab","flink":"C:\\Temp\\HncDownload\\hupdate.cab","fbyte":"21796","ftype":".cab","ftime":"2018-10-10 오전 9:29:21"},{"fname":"Update.log","flink":"C:\\Temp\\HncDownload\\Update.log","fbyte":"743","ftype":".log","ftime":"2018-10-10 오전 9:29:24"},{"fname":"HncUtils.cab","flink":"C:\\Temp\\HncDownload\\HncUtils\\HncUtils.cab","fbyte":"14125","ftype":".cab","ftime":"2018-10-10 오전 9:29:24"},{"fname":"HOffice90.cab","flink":"C:\\Temp\\HncDownload\\HOffice90\\HOffice90.cab","fbyte":"21606","ftype":".cab","ftime":"2018-10-10 오전 9:29:22"},{"fname":"HncUpdate.cab","flink":"C:\\Temp\\HncDownload\\PrepareInstallTemp\\HncUpdate.cab","fbyte":"65458","ftype":".cab","ftime":"2018-10-10 오전 9:29:24"},{"fname":"Common90.cab","flink":"C:\\Temp\\HncDownload\\PrepareTemp\\Common90.cab","fbyte":"21397","ftype":".cab","ftime":"2018-10-10 오전 9:29:22"},{"fname":"HCell90.cab","flink":"C:\\Temp\\HncDownload\\PrepareTemp\\HCell90.cab","fbyte":"21292","ftype":".cab","ftime":"2018-10-10 오전 9:29:22"},{"fname":"HncDic90.cab","flink":"C:\\Temp\\HncDownload\\PrepareTemp\\HncDic90.cab","fbyte":"21245","ftype":".cab","ftime":"2018-10-10 오전 9:29:22"},{"fname":"HncFinder90.cab","flink":"C:\\Temp\\HncDownload\\PrepareTemp\\HncFinder90.cab","fbyte":"21248","ftype":".cab","ftime":"2018-10-10 오전 9:29:22"},{"fname":"HncPrivacy90.cab","flink":"C:\\Temp\\HncDownload\\PrepareTemp\\HncPrivacy90.cab","fbyte":"21257","ftype":".cab","ftime":"2018-10-10 오전 9:29:22"},{"fname":"HncTT90.cab","flink":"C:\\Temp\\HncDownload\\PrepareTemp\\HncTT90.cab","fbyte":"21252","ftype":".cab","ftime":"2018-10-10 오전 9:29:23"},{"fname":"HncUpdate.cab","flink":"C:\\Temp\\HncDownload\\PrepareTemp\\HncUpdate.cab","fbyte":"14030","ftype":".cab","ftime":"2018-10-10 오전 9:29:24"},{"fname":"HShow90.cab","flink":"C:\\Temp\\HncDownload\\PrepareTemp\\HShow90.cab","fbyte":"21300","ftype":".cab","ftime":"2018-10-10 오전 9:29:22"},{"fname":"Hwp90.cab","flink":"C:\\Temp\\HncDownload\\PrepareTemp\\Hwp90.cab","fbyte":"21298","ftype":".cab","ftime":"2018-10-10 오전 9:29:22"},{"fname":"HwpTemplate.cab","flink":"C:\\Temp\\HncDownload\\PrepareTemp\\HwpTemplate.cab","fbyte":"21256","ftype":".cab","ftime":"2018-10-10 오전 9:29:23"},{"fname":"PubDocFilter.cab","flink":"C:\\Temp\\HncDownload\\PrepareTemp\\PubDocFilter.cab","fbyte":"21249","ftype":".cab","ftime":"2018-10-10 오전 9:29:23"},{"fname":"TTF.cab","flink":"C:\\Temp\\HncDownload\\PrepareTemp\\TTF.cab","fbyte":"21224","ftype":".cab","ftime":"2018-10-10 오전 9:29:23"},{"fname":"WINTTF.cab","flink":"C:\\Temp\\HncDownload\\PrepareTemp\\WINTTF.cab","fbyte":"21243","ftype":".cab","ftime":"2018-10-10 오전 9:29:23"},{"fname":"cert_chain.pem.enc","flink":"C:\\Temp\\ssl\\cur\\cert_chain.pem.enc","fbyte":"2912","ftype":".enc","ftime":"2016-11-30 오후 2:49:22"},{"fname":"client_cert.pem.enc","flink":"C:\\Temp\\ssl\\cur\\client_cert.pem.enc","fbyte":"3920","ftype":".enc","ftime":"2016-11-30 오후 2:49:22"},{"fname":"client_key.pem.enc","flink":"C:\\Temp\\ssl\\cur\\client_key.pem.enc","fbyte":"1744","ftype":".enc","ftime":"2016-11-30 오후 2:49:22"},{"fname":"cli_pass_phrase.enc","flink":"C:\\Temp\\ssl\\cur\\cli_pass_phrase.enc","fbyte":"16","ftype":".enc","ftime":"2016-11-30 오후 2:49:22"},{"fname":"cert_chain.pem.enc","flink":"C:\\Temp\\ssl\\new\\cert_chain.pem.enc","fbyte":"2912","ftype":".enc","ftime":"2016-11-30 오후 2:49:22"},{"fname":"client_cert.pem.enc","flink":"C:\\Temp\\ssl\\new\\client_cert.pem.enc","fbyte":"3920","ftype":".enc","ftime":"2016-11-30 오후 2:49:22"},{"fname":"client_key.pem.enc","flink":"C:\\Temp\\ssl\\new\\client_key.pem.enc","fbyte":"1744","ftype":".enc","ftime":"2016-11-30 오후 2:49:22"}]}